qc_structure/__init__.py
qc_structure/core.py
qc_structure/models.py
qc_structure/utils.py
qc_structure-0.1.1.dist-info/licenses/LICENSE
qc_structure-0.1.1.dist-info/METADATA
qc_structure-0.1.1.dist-info/WHEEL
qc_structure-0.1.1.dist-info/top_level.txt
qc_structure-0.1.1.dist-info/RECORD
