Metadata-Version: 2.4
Name: qc-structure
Version: 0.1.1
Summary: 入試問題構造情報ライブラリ - WordファイルとJSON構造データを統合処理
Author-email: kamarume <akamarume@icloud.com>
License: MIT
Project-URL: Homepage, https://github.com/kamarume/qc-structure
Project-URL: Repository, https://github.com/kamarume/qc-structure
Project-URL: Issues, https://github.com/kamarume/qc-structure/issues
Keywords: word,docx,structure,exam,質保証,QC
Classifier: Development Status :: 3 - Alpha
Classifier: Intended Audience :: Developers
Classifier: License :: OSI Approved :: MIT License
Classifier: Programming Language :: Python :: 3
Classifier: Programming Language :: Python :: 3.7
Classifier: Programming Language :: Python :: 3.8
Classifier: Programming Language :: Python :: 3.9
Classifier: Programming Language :: Python :: 3.10
Classifier: Programming Language :: Python :: 3.11
Classifier: Programming Language :: Python :: 3.12
Classifier: Topic :: Software Development :: Libraries :: Python Modules
Classifier: Topic :: Text Processing
Requires-Python: >=3.7
License-File: LICENSE
Requires-Dist: python-docx>=0.8.11
Dynamic: license-file
